MANIFEST.in
README.md
setup.cfg
setup.py
embrion/__init__.py
embrion/cli.py
embrion/docker-compose.yml
embrion.egg-info/PKG-INFO
embrion.egg-info/SOURCES.txt
embrion.egg-info/dependency_links.txt
embrion.egg-info/entry_points.txt
embrion.egg-info/requires.txt
embrion.egg-info/top_level.txt
embrion/dev/Dockerfile
embrion/dev/environment.yml
embrion/dev/environment_extra.yml
embrion/dev/environment_init.yml
embrion/dev/refresh_environment.sh
embrion/dev/startup.sh
embrion/dev/scripts/create_environment.sh
embrion/dev/scripts/remove_environment.sh
embrion/dev/scripts/update_environment.sh
embrion/src/__init__.py
embrion/src/docker_engine.py
embrion/src/remote_engine.py
embrion/src/storage.py
embrion/src/util.py