Metadata-Version: 1.0
Name: embrion
Version: 0.2.0
Summary: UNKNOWN
Home-page: https://gitlab.com/izel93/embrion
Author: Izel Levy
Author-email: izel93@gmail.com
License: MIT
Keywords: development,environment,docker
Platform: UNKNOWN
